memdof/__init__.py
memdof/membranes.py
memdof/mtypes.py
memdof/topologies.py
memdof-0.1.3.dist-info/LICENSE
memdof-0.1.3.dist-info/METADATA
memdof-0.1.3.dist-info/WHEEL
memdof-0.1.3.dist-info/top_level.txt
memdof-0.1.3.dist-info/RECORD
