Metadata-Version: 2.1
Name: memdof
Version: 0.1.3
Summary: A python package to determine the internal degrees of freedom for a single lipid membrane.
Home-page: https://github.com/NoxelS/memdof
Author: Noel Schwabenland
Author-email: noel@lusi.uni-sb.de
License: MIT
Classifier: Development Status :: 1 - Planning
Classifier: Intended Audience :: Science/Research
Classifier: Topic :: Scientific/Engineering :: Bio-Informatics
Classifier: Topic :: Scientific/Engineering :: Physics
Classifier: License :: OSI Approved :: MIT License
Classifier: Operating System :: POSIX :: Linux
Classifier: Programming Language :: Python :: 3.9
Classifier: Typing :: Typed
License-File: LICENSE
Requires-Dist: numpy (>=1.21.5)
Requires-Dist: biopython (>=1.81)
